[{"Date":"04-12-2021","DailyStatistics":{"CountOfRecords":1000000,"CountOfValidRecords":500000,"CountOfInvalidRecords":500000},"DateInFormat":"2021-12-04T00:00:00"},{"Date":"03-12-2021","DailyStatistics":{"CountOfRecords":126255,"CountOfValidRecords":47400,"CountOfInvalidRecords":79565},"DateInFormat":"2021-12-03T00:00:00"},{"Date":"02-12-2021","DailyStatistics":{"CountOfRecords":126295,"CountOfValidRecords":47290,"CountOfInvalidRecords":78565},"DateInFormat":"2021-12-02T00:00:00"},{"Date":"04-11-2021","DailyStatistics":{"CountOfRecords":1262985,"CountOfValidRecords":440290,"CountOfInvalidRecords":789565},"DateInFormat":"2021-11-04T00:00:00"},{"Date":"05-11-2021","DailyStatistics":{"CountOfRecords":1262985,"CountOfValidRecords":474290,"CountOfInvalidRecords":788565},"DateInFormat":"2021-11-05T00:00:00"},{"Date":"03-11-2021","DailyStatistics":{"CountOfRecords":129855,"CountOfValidRecords":47290,"CountOfInvalidRecords":79565},"DateInFormat":"2021-11-03T00:00:00"}]